ps_py/__init__.py
ps_py/subscriber.py
ps_py/utils.py
ps_py/contrib/__init__.py
ps_py/contrib/merge.py
ps_py/contrib/ofsubject.py
ps_py/contrib/pipe_map.py
ps_py/publisher/__init__.py
ps_py/publisher/base.py
ps_py/publisher/publisher.py
ps_py/subject/__init__.py
ps_py/subject/base.py
ps_py/subject/subject.py
tests/__init__.py
tests/constants.py
tests/test_contrib.py
tests/test_publisher.py
tests/test_subject.py
tests/test_subscriber.py
ps_py-1.0.0.1.dist-info/LICENCE
ps_py-1.0.0.1.dist-info/METADATA
ps_py-1.0.0.1.dist-info/WHEEL
ps_py-1.0.0.1.dist-info/top_level.txt
ps_py-1.0.0.1.dist-info/RECORD
