Metadata-Version: 2.1
Name: ps-py
Version: 1.0.0.1
Summary: PubSubPython
Home-page: https://github.com/midhuncnair/ps_py
Author: Midhun C Nair
Author-email: midhunch@gmail.com
License: MIT LICENSE
Keywords: publisher,subscriber,pub,sub,events,observable,subscribe,pub-sub-python,ps_py
Platform: UNKNOWN
Classifier: Programming Language :: Python :: 3
Classifier: License :: OSI Approved :: MIT License
Classifier: Operating System :: OS Independent
Requires-Python: >=3.5.9
